discord/__init__.py
discord/__main__.py
discord/abc.py
discord/activity.py
discord/audit_logs.py
discord/backoff.py
discord/calls.py
discord/channel.py
discord/client.py
discord/colour.py
discord/context_managers.py
discord/embeds.py
discord/emoji.py
discord/enums.py
discord/errors.py
discord/file.py
discord/gateway.py
discord/guild.py
discord/http.py
discord/invite.py
discord/iterators.py
discord/member.py
discord/message.py
discord/mixins.py
discord/object.py
discord/opus.py
discord/permissions.py
discord/player.py
discord/raw_models.py
discord/reaction.py
discord/relationship.py
discord/role.py
discord/shard.py
discord/state.py
discord/user.py
discord/utils.py
discord/voice_client.py
discord/webhook.py
discord/ext/commands/__init__.py
discord/ext/commands/bot.py
discord/ext/commands/context.py
discord/ext/commands/converter.py
discord/ext/commands/cooldowns.py
discord/ext/commands/core.py
discord/ext/commands/errors.py
discord/ext/commands/formatter.py
discord/ext/commands/view.py
redbot/__init__.py
redbot/__main__.py
redbot/launcher.py
redbot/meta.py
redbot/setup.py
redbot/cogs/__init__.py
redbot/cogs/admin/__init__.py
redbot/cogs/admin/admin.py
redbot/cogs/admin/announcer.py
redbot/cogs/admin/converters.py
redbot/cogs/admin/locales/ar-SA.po
redbot/cogs/admin/locales/bg-BG.po
redbot/cogs/admin/locales/da-DK.po
redbot/cogs/admin/locales/de-DE.po
redbot/cogs/admin/locales/el-GR.po
redbot/cogs/admin/locales/en-PT.po
redbot/cogs/admin/locales/es-ES.po
redbot/cogs/admin/locales/fi-FI.po
redbot/cogs/admin/locales/fr-FR.po
redbot/cogs/admin/locales/hu-HU.po
redbot/cogs/admin/locales/id-ID.po
redbot/cogs/admin/locales/it-IT.po
redbot/cogs/admin/locales/ja-JP.po
redbot/cogs/admin/locales/ko-KR.po
redbot/cogs/admin/locales/lol-US.po
redbot/cogs/admin/locales/nl-NL.po
redbot/cogs/admin/locales/no-NO.po
redbot/cogs/admin/locales/pl-PL.po
redbot/cogs/admin/locales/pt-BR.po
redbot/cogs/admin/locales/pt-PT.po
redbot/cogs/admin/locales/ru-RU.po
BotEXBotBase-3.1.3.dist-info/LICENSE
BotEXBotBase-3.1.3.dist-info/METADATA
BotEXBotBase-3.1.3.dist-info/WHEEL
BotEXBotBase-3.1.3.dist-info/entry_points.txt
BotEXBotBase-3.1.3.dist-info/top_level.txt
BotEXBotBase-3.1.3.dist-info/RECORD
